md_mermaid.py
md_mermaid-0.1.1.dist-info/LICENSE
md_mermaid-0.1.1.dist-info/METADATA
md_mermaid-0.1.1.dist-info/WHEEL
md_mermaid-0.1.1.dist-info/top_level.txt
md_mermaid-0.1.1.dist-info/RECORD
