Metadata-Version: 2.1
Name: md_mermaid
Version: 0.1.1
Summary: Python-Markdown extension to add support for mermaid graph inside markdown file.
Home-page: https://github.com/oruelle/md_mermaid
Author: Olivier Ruelle
Author-email: olivier.ruelle@yahoo.com
License: UNKNOWN
Platform: UNKNOWN
Classifier: Development Status :: 4 - Beta
Classifier: Operating System :: OS Independent
Classifier: License :: OSI Approved :: GNU General Public License v3 (GPLv3)
Classifier: Intended Audience :: Developers
Classifier: Programming Language :: Python
Classifier: Topic :: Text Processing :: Filters
Classifier: Topic :: Text Processing :: Markup :: HTML
